breathmetrics/__init__.py
breathmetrics/main.py
breathmetrics/breathmetrics_function/__init__.py
breathmetrics/breathmetrics_function/createBreathmetricsData.py
breathmetrics/breathmetrics_function/getBreathingRate.py
breathmetrics/breathmetrics_function/getInhaleExhaleonsets.py
breathmetrics/breathmetrics_function/getTidalVolume.py
breathmetrics/preprocessing/__init__.py
breathmetrics/preprocessing/cleaningExhaleOnsets.py
breathmetrics/preprocessing/cleaningInhaleOnsets.py
breathmetrics/utils/__init__.py
breathmetrics/utils/average_list.py
breathmetrics/utils/delete_outliers.py
breathmetrics/utils/flatten_list.py
breathmetrics/utils/multiplot.py
breathmetrics-0.1.8.dist-info/METADATA
breathmetrics-0.1.8.dist-info/WHEEL
breathmetrics-0.1.8.dist-info/top_level.txt
breathmetrics-0.1.8.dist-info/RECORD
