Metadata-Version: 2.1
Name: breathmetrics
Version: 0.1.8
Summary: A breathing analysis tool
Author: Shashank
Author-email: shashankchandrashekar2000@gmail.com
Classifier: Programming Language :: Python :: 3
Classifier: License :: OSI Approved :: MIT License
Classifier: Operating System :: OS Independent
Requires-Python: >=3.10
Requires-Dist: contourpy ==1.2.1
Requires-Dist: cycler ==0.12.1
Requires-Dist: fonttools ==4.53.0
Requires-Dist: joblib ==1.4.2
Requires-Dist: kiwisolver ==1.4.5
Requires-Dist: matplotlib ==3.9.0
Requires-Dist: numpy ==1.26.4
Requires-Dist: packaging ==24.1
Requires-Dist: pandas ==2.2.2
Requires-Dist: pillow ==10.3.0
Requires-Dist: pyparsing ==3.1.2
Requires-Dist: python-dateutil ==2.9.0.post0
Requires-Dist: pytz ==2024.1
Requires-Dist: scikit-learn ==1.5.0
Requires-Dist: scipy ==1.13.1
Requires-Dist: six ==1.16.0
Requires-Dist: threadpoolctl ==3.5.0
Requires-Dist: tzdata ==2024.1
